morinkit/__init__.py
morinkit/convert.py
morinkit/exceptions.py
morinkit/maf.py
morinkit/morinkit.py
morinkit/process.py
morinkit/summarize.py
morinkit/ui.py
morinkit/utils.py
morinkit/vcf.py
morinkit-0.1.3.dist-info/DESCRIPTION.rst
morinkit-0.1.3.dist-info/METADATA
morinkit-0.1.3.dist-info/RECORD
morinkit-0.1.3.dist-info/WHEEL
morinkit-0.1.3.dist-info/entry_points.txt
morinkit-0.1.3.dist-info/metadata.json
morinkit-0.1.3.dist-info/top_level.txt
