Metadata-Version: 2.0
Name: morinkit
Version: 0.1.3
Summary: Python functions for cancer genomics
Home-page: https://github.com/morinlab/morinkit
Author: Morin Lab Members (Bruno Grande)
Author-email: morinlab@sfu.ca
License: GNU GPLv3
Keywords: bioinformatics cancer genomics utility tool
Platform: UNKNOWN
Classifier: Development Status :: 3 - Alpha
Classifier: Intended Audience :: Science/Research
Classifier: License :: OSI Approved :: GNU General Public License v3 (GPLv3)
Classifier: Programming Language :: Python :: 3 :: Only
Classifier: Programming Language :: Python :: 3.3
Classifier: Programming Language :: Python :: 3.4
Classifier: Programming Language :: Python :: 3.5
Classifier: Topic :: Scientific/Engineering :: Bio-Informatics
Requires-Dist: Cython
Requires-Dist: cyvcf2
Requires-Dist: numpy
Requires-Dist: pysam
